CHANGES.txt
LICENSE.txt
MANIFEST.in
README.txt
setup.py
bin/g2g
docs/Makefile
docs/README.txt
docs/make.bat
docs/source/best_practice.rst
docs/source/compatibility.rst
docs/source/conf.py
docs/source/configuring.rst
docs/source/gallery.rst
docs/source/index.rst
docs/source/installing.rst
docs/source/quickstart.rst
docs/source/resources.rst
docs/source/results.rst
docs/source/using.rst
docs/source/images/all_response_times_1.png
docs/source/images/all_response_times_2.png
docs/source/images/all_tps_stacked.png
docs/source/images/new_connections.png
docs/source/images/response_time_components.png
docs/source/images/response_time_groups.png
g2g/__init__.py
g2g/engine.py
g2g/g2g_config.py
g2g/aggregator/__init__.py
g2g/aggregator/http.py
g2g/aggregator/non_http.py
g2g/logtype/__init__.py
g2g/logtype/grinder/__init__.py
g2g/logtype/grinder/column_map.py
g2g/logtype/grinder/mapping_reader.py
g2g/logtype/grinder/transaction.py
grinder_to_graphite.egg-info/PKG-INFO
grinder_to_graphite.egg-info/SOURCES.txt
grinder_to_graphite.egg-info/dependency_links.txt
grinder_to_graphite.egg-info/requires.txt
grinder_to_graphite.egg-info/top_level.txt
test/test_config.py
test/test_engine.py
test/test_g2g.py
test/test_http_aggregator.py
test/test_mapping_reader.py
test/test_non_http_aggregator.py
test/test_transaction.py