Metadata-Version: 1.0
Name: grinder-to-graphite
Version: 0.1.1
Summary: Ingests data from Grinder logs into Graphite where it can be visualized.
Home-page: https://grinder_to_graphite.readthedocs.org/en/latest/
Author: Travis Bear
Author-email: travis_bear@yahoo.com
License: LICENSE.txt
Keywords: graphite grinder logster logs
Platform: UNKNOWN
